py_pdlrens2code/__init__.py
py_pdlrens2code/cli.py
py_pdlrens2code/py_pdlrens2code.py
py_pdlrens2code-0.1.0.dist-info/AUTHORS.rst
py_pdlrens2code-0.1.0.dist-info/LICENSE
py_pdlrens2code-0.1.0.dist-info/METADATA
py_pdlrens2code-0.1.0.dist-info/WHEEL
py_pdlrens2code-0.1.0.dist-info/entry_points.txt
py_pdlrens2code-0.1.0.dist-info/top_level.txt
py_pdlrens2code-0.1.0.dist-info/RECORD
